edge_impulse_linux/__init__.py
edge_impulse_linux/audio.py
edge_impulse_linux/image.py
edge_impulse_linux/runner.py
edgeimpulse/__init__.py
edgeimpulse/audio.py
edgeimpulse/image.py
edgeimpulse/runner.py
edge_impulse_linux-1.0.0.dist-info/LICENSE
edge_impulse_linux-1.0.0.dist-info/METADATA
edge_impulse_linux-1.0.0.dist-info/WHEEL
edge_impulse_linux-1.0.0.dist-info/top_level.txt
edge_impulse_linux-1.0.0.dist-info/RECORD
