Metadata-Version: 2.1
Name: edge-impulse-linux
Version: 1.0.0
Summary: Python runner for real-time ML classification
Home-page: https://github.com/edgeimpulse/linux-sdk-python
Author: EdgeImpulse Inc.
Author-email: hello@edgeimpulse.com
License: UNKNOWN
Project-URL: Bug Tracker, https://github.com/edgeimpulse/linux-sdk-python/issues
Platform: UNKNOWN
Classifier: Programming Language :: Python :: 3
Classifier: License :: OSI Approved :: Apache Software License
Classifier: Operating System :: OS Independent
Requires-Python: >=3.7
Requires-Dist: numpy (==1.19)
Requires-Dist: opencv-python (==4.5.1.48)
Requires-Dist: PyAudio (==0.2.11)
Requires-Dist: psutil (==5.8.0)
